spicypy/__init__.py
spicypy/control/__init__.py
spicypy/control/system.py
spicypy/control/utils.py
spicypy/signal/__init__.py
spicypy/signal/coherent_subtraction.py
spicypy/signal/filter.py
spicypy/signal/frequency_series.py
spicypy/signal/spectral/__init__.py
spicypy/signal/spectral/_csd_daniell.py
spicypy/signal/spectral/_lpsd.py
spicypy/signal/spectrogram.py
spicypy/signal/time_series.py
spicypy/signal/transfer_function.py
spicypy/signal/wiener_filter.py
spicypy-1.0.dist-info/AUTHORS.rst
spicypy-1.0.dist-info/LICENSE.txt
spicypy-1.0.dist-info/METADATA
spicypy-1.0.dist-info/WHEEL
spicypy-1.0.dist-info/RECORD
